{
  "configVersion": 1,
  "timestamp": 1686997428932,
  "index": "https://hoangvu1104.github.io/VmuSuperLeague2023/index.html",
  "assetGroups": [
    {
      "name": "app",
      "installMode": "prefetch",
      "updateMode": "prefetch",
      "cacheQueryOptions": {
        "ignoreVary": true
      },
      "urls": [
        "https://hoangvu1104.github.io/VmuSuperLeague2023/1033.0d4c404c719a46a0.js",
        "https://hoangvu1104.github.io/VmuSuperLeague2023/1118.5c7d9adb7ea3c9fe.js",
        "https://hoangvu1104.github.io/VmuSuperLeague2023/1186.c1f153c234d1165a.js",
        "https://hoangvu1104.github.io/VmuSuperLeague2023/1217.18a0b4056950e18c.js",
        "https://hoangvu1104.github.io/VmuSuperLeague2023/1536.e6fd0866682c671f.js",
        "https://hoangvu1104.github.io/VmuSuperLeague2023/1650.86a51fc754eca05d.js",
        "https://hoangvu1104.github.io/VmuSuperLeague2023/1709.7afcbbad72075979.js",
        "https://hoangvu1104.github.io/VmuSuperLeague2023/2073.7f25f0ac59e521b2.js",
        "https://hoangvu1104.github.io/VmuSuperLeague2023/2175.1c0a0e7db2d04198.js",
        "https://hoangvu1104.github.io/VmuSuperLeague2023/2289.cc38e951226c164f.js",
        "https://hoangvu1104.github.io/VmuSuperLeague2023/2349.2d244b3a045338c0.js",
        "https://hoangvu1104.github.io/VmuSuperLeague2023/2698.118cf490b992512b.js",
        "https://hoangvu1104.github.io/VmuSuperLeague2023/2773.6bb9d3cd3be6c394.js",
        "https://hoangvu1104.github.io/VmuSuperLeague2023/3236.3fd1993c538c65e7.js",
        "https://hoangvu1104.github.io/VmuSuperLeague2023/3648.941ce2e12909a18b.js",
        "https://hoangvu1104.github.io/VmuSuperLeague2023/3804.29e3a34d0dae3e23.js",
        "https://hoangvu1104.github.io/VmuSuperLeague2023/388.6f2d8f047fa7b893.js",
        "https://hoangvu1104.github.io/VmuSuperLeague2023/4174.d9562d521e0fd60f.js",
        "https://hoangvu1104.github.io/VmuSuperLeague2023/4330.0ead012ae55b4dd6.js",
        "https://hoangvu1104.github.io/VmuSuperLeague2023/4376.acdbdbf47b6eabf0.js",
        "https://hoangvu1104.github.io/VmuSuperLeague2023/438.0c894ccae61e4cf3.js",
        "https://hoangvu1104.github.io/VmuSuperLeague2023/4432.e7e0ff993fbbc09c.js",
        "https://hoangvu1104.github.io/VmuSuperLeague2023/4651.09bae089c037779c.js",
        "https://hoangvu1104.github.io/VmuSuperLeague2023/4711.f099977709a93521.js",
        "https://hoangvu1104.github.io/VmuSuperLeague2023/4753.8ce67b175f1f0d7e.js",
        "https://hoangvu1104.github.io/VmuSuperLeague2023/4908.9e23194057556798.js",
        "https://hoangvu1104.github.io/VmuSuperLeague2023/4959.dc2f7d1857d2c212.js",
        "https://hoangvu1104.github.io/VmuSuperLeague2023/5168.b871efd2f80b66df.js",
        "https://hoangvu1104.github.io/VmuSuperLeague2023/5227.be79798bc07bfd2d.js",
        "https://hoangvu1104.github.io/VmuSuperLeague2023/5326.07fb26899d6275e6.js",
        "https://hoangvu1104.github.io/VmuSuperLeague2023/5349.db97e0bcf0b1d5c7.js",
        "https://hoangvu1104.github.io/VmuSuperLeague2023/5652.5b508cdc944e8cdb.js",
        "https://hoangvu1104.github.io/VmuSuperLeague2023/5817.939459b690f37977.js",
        "https://hoangvu1104.github.io/VmuSuperLeague2023/5836.1afb40a2f2e8a43e.js",
        "https://hoangvu1104.github.io/VmuSuperLeague2023/6120.e10bd97ad0fdb89d.js",
        "https://hoangvu1104.github.io/VmuSuperLeague2023/6560.3af818bd483d0781.js",
        "https://hoangvu1104.github.io/VmuSuperLeague2023/657.0100b94c3ab93a48.js",
        "https://hoangvu1104.github.io/VmuSuperLeague2023/7070.ae1efda2cc33decc.js",
        "https://hoangvu1104.github.io/VmuSuperLeague2023/7206.87b4e433ec6bffb4.js",
        "https://hoangvu1104.github.io/VmuSuperLeague2023/7544.67b20d4a761e2e38.js",
        "https://hoangvu1104.github.io/VmuSuperLeague2023/7602.90dc1e3a0c9814c8.js",
        "https://hoangvu1104.github.io/VmuSuperLeague2023/8136.78410c20f1e863f9.js",
        "https://hoangvu1104.github.io/VmuSuperLeague2023/8628.a088c1cf13dc93d1.js",
        "https://hoangvu1104.github.io/VmuSuperLeague2023/8766.86553a4073f31820.js",
        "https://hoangvu1104.github.io/VmuSuperLeague2023/8939.4734c10cd219622c.js",
        "https://hoangvu1104.github.io/VmuSuperLeague2023/9016.c5274acf0968a2f2.js",
        "https://hoangvu1104.github.io/VmuSuperLeague2023/9230.757cd67fca66f432.js",
        "https://hoangvu1104.github.io/VmuSuperLeague2023/9325.5c0b1857766135de.js",
        "https://hoangvu1104.github.io/VmuSuperLeague2023/9434.84524f87282c285c.js",
        "https://hoangvu1104.github.io/VmuSuperLeague2023/9536.65a8da2947d76848.js",
        "https://hoangvu1104.github.io/VmuSuperLeague2023/9654.97231d17e99b6667.js",
        "https://hoangvu1104.github.io/VmuSuperLeague2023/9824.c512b904cf4c8833.js",
        "https://hoangvu1104.github.io/VmuSuperLeague2023/9922.44ec96e4d7f86d18.js",
        "https://hoangvu1104.github.io/VmuSuperLeague2023/9958.3a7943046d5c3504.js",
        "https://hoangvu1104.github.io/VmuSuperLeague2023/common.46ff48aafb75616f.js",
        "https://hoangvu1104.github.io/VmuSuperLeague2023/index.html",
        "https://hoangvu1104.github.io/VmuSuperLeague2023/main.0a6797d4ff3f8d97.js",
        "https://hoangvu1104.github.io/VmuSuperLeague2023/manifest.webmanifest",
        "https://hoangvu1104.github.io/VmuSuperLeague2023/polyfills-core-js.20e9fb5568c66479.js",
        "https://hoangvu1104.github.io/VmuSuperLeague2023/polyfills-dom.3a5e3168052f1fc5.js",
        "https://hoangvu1104.github.io/VmuSuperLeague2023/polyfills.fc6fad8ce607b49d.js",
        "https://hoangvu1104.github.io/VmuSuperLeague2023/runtime.2751a647548631ba.js",
        "https://hoangvu1104.github.io/VmuSuperLeague2023/styles.b8777235688abb5b.css"
      ],
      "patterns": []
    },
    {
      "name": "assets",
      "installMode": "lazy",
      "updateMode": "prefetch",
      "cacheQueryOptions": {
        "ignoreVary": true
      },
      "urls": [
        "https://hoangvu1104.github.io/VmuSuperLeague2023/assets/icon/favicon.png",
        "https://hoangvu1104.github.io/VmuSuperLeague2023/assets/icons/icon-128x128.png",
        "https://hoangvu1104.github.io/VmuSuperLeague2023/assets/icons/icon-144x144.png",
        "https://hoangvu1104.github.io/VmuSuperLeague2023/assets/icons/icon-152x152.png",
        "https://hoangvu1104.github.io/VmuSuperLeague2023/assets/icons/icon-192x192.png",
        "https://hoangvu1104.github.io/VmuSuperLeague2023/assets/icons/icon-384x384.png",
        "https://hoangvu1104.github.io/VmuSuperLeague2023/assets/icons/icon-512x512.png",
        "https://hoangvu1104.github.io/VmuSuperLeague2023/assets/icons/icon-72x72.png",
        "https://hoangvu1104.github.io/VmuSuperLeague2023/assets/icons/icon-96x96.png",
        "https://hoangvu1104.github.io/VmuSuperLeague2023/assets/images/3MienFC.jpg",
        "https://hoangvu1104.github.io/VmuSuperLeague2023/assets/images/BFC.JPG",
        "https://hoangvu1104.github.io/VmuSuperLeague2023/assets/images/BlueTeam.jpg",
        "https://hoangvu1104.github.io/VmuSuperLeague2023/assets/images/Logo.png",
        "https://hoangvu1104.github.io/VmuSuperLeague2023/assets/images/OrangeTeam.jpg",
        "https://hoangvu1104.github.io/VmuSuperLeague2023/assets/images/PinkBlueTeam.jpg",
        "https://hoangvu1104.github.io/VmuSuperLeague2023/assets/images/PinkTeam.jpg",
        "https://hoangvu1104.github.io/VmuSuperLeague2023/assets/images/PinkTeam2.jpg",
        "https://hoangvu1104.github.io/VmuSuperLeague2023/assets/images/RBJunior.JPG",
        "https://hoangvu1104.github.io/VmuSuperLeague2023/assets/images/RedTeam.jpg",
        "https://hoangvu1104.github.io/VmuSuperLeague2023/assets/images/Stechco.png",
        "https://hoangvu1104.github.io/VmuSuperLeague2023/assets/images/SuperCup.jpg",
        "https://hoangvu1104.github.io/VmuSuperLeague2023/assets/images/U45FC - Copy.jpg",
        "https://hoangvu1104.github.io/VmuSuperLeague2023/assets/images/U45FC.jpg",
        "https://hoangvu1104.github.io/VmuSuperLeague2023/assets/images/VMU.jpg",
        "https://hoangvu1104.github.io/VmuSuperLeague2023/assets/images/WhiteTeam.jpg",
        "https://hoangvu1104.github.io/VmuSuperLeague2023/assets/images/YellowTeam.jpg",
        "https://hoangvu1104.github.io/VmuSuperLeague2023/assets/shapes.svg"
      ],
      "patterns": []
    }
  ],
  "dataGroups": [],
  "hashTable": {
    "https://hoangvu1104.github.io/VmuSuperLeague2023/1033.0d4c404c719a46a0.js": "06b06cf36ada647642be8968be8f0e528331ca07",
    "https://hoangvu1104.github.io/VmuSuperLeague2023/1118.5c7d9adb7ea3c9fe.js": "9f3fc66c00e1c287ccddac638b4447e9cd3b4813",
    "https://hoangvu1104.github.io/VmuSuperLeague2023/1186.c1f153c234d1165a.js": "40660d85661e39125758594b1da7b6b1434abd2e",
    "https://hoangvu1104.github.io/VmuSuperLeague2023/1217.18a0b4056950e18c.js": "33c5b2cf32595e16b9d13b920a320228c15bb36e",
    "https://hoangvu1104.github.io/VmuSuperLeague2023/1536.e6fd0866682c671f.js": "a9a772690ae9e8c8ac86f021f1c5eea4d6e4e998",
    "https://hoangvu1104.github.io/VmuSuperLeague2023/1650.86a51fc754eca05d.js": "bef99193f730e704c8fb8559cd98c7efbd47a6f9",
    "https://hoangvu1104.github.io/VmuSuperLeague2023/1709.7afcbbad72075979.js": "066ddd57bc92ca26a9ee33666342056899a0c371",
    "https://hoangvu1104.github.io/VmuSuperLeague2023/2073.7f25f0ac59e521b2.js": "ff61a1c778f6566b082461ada4e31bea2c986168",
    "https://hoangvu1104.github.io/VmuSuperLeague2023/2175.1c0a0e7db2d04198.js": "5cc481237e0cb58475bee7e947ee066130fc4ee2",
    "https://hoangvu1104.github.io/VmuSuperLeague2023/2289.cc38e951226c164f.js": "6e5de7224a0052210377cf36092c8fcbe1a2d078",
    "https://hoangvu1104.github.io/VmuSuperLeague2023/2349.2d244b3a045338c0.js": "796f6926aab8f5fed7d7bce15c11f6dc200d87de",
    "https://hoangvu1104.github.io/VmuSuperLeague2023/2698.118cf490b992512b.js": "a8a0defea6184b3ffb0d109d9dc999e0855f64f2",
    "https://hoangvu1104.github.io/VmuSuperLeague2023/2773.6bb9d3cd3be6c394.js": "26590f1084a4b3d75b45f2c6adf1a2dfe3eedbcd",
    "https://hoangvu1104.github.io/VmuSuperLeague2023/3236.3fd1993c538c65e7.js": "3a893d377572ad96a74aa8fcac950d0b53f25abd",
    "https://hoangvu1104.github.io/VmuSuperLeague2023/3648.941ce2e12909a18b.js": "1b2bce67a8ef0c4fb49b8517cadd654326166364",
    "https://hoangvu1104.github.io/VmuSuperLeague2023/3804.29e3a34d0dae3e23.js": "4237f1d26673be24453e1b3275d9bf1726c95fc9",
    "https://hoangvu1104.github.io/VmuSuperLeague2023/388.6f2d8f047fa7b893.js": "410770bd0240b0e6280bf7280ddc395fbec89a28",
    "https://hoangvu1104.github.io/VmuSuperLeague2023/4174.d9562d521e0fd60f.js": "3d68ead59ab48f272e9262b01b096c4c0de9446c",
    "https://hoangvu1104.github.io/VmuSuperLeague2023/4330.0ead012ae55b4dd6.js": "f5f7ad4e969d7333d5d82d81164823fb2df49176",
    "https://hoangvu1104.github.io/VmuSuperLeague2023/4376.acdbdbf47b6eabf0.js": "c5365f342601bfa9d877cba7ff4511864727d71e",
    "https://hoangvu1104.github.io/VmuSuperLeague2023/438.0c894ccae61e4cf3.js": "f8d3276dfe96c1f0af3c06a46cda9fc9b23d9330",
    "https://hoangvu1104.github.io/VmuSuperLeague2023/4432.e7e0ff993fbbc09c.js": "3c6930a45718150da82c9a529aeb643092021c04",
    "https://hoangvu1104.github.io/VmuSuperLeague2023/4651.09bae089c037779c.js": "1a9e88f995c5dad2a3d4f64b36b5d8c5f4fd6b74",
    "https://hoangvu1104.github.io/VmuSuperLeague2023/4711.f099977709a93521.js": "94c2a2a3aaed858b194241cebf2dc1ec904f4fa0",
    "https://hoangvu1104.github.io/VmuSuperLeague2023/4753.8ce67b175f1f0d7e.js": "eea5265088da844594927daf1a344ccd403ce8c4",
    "https://hoangvu1104.github.io/VmuSuperLeague2023/4908.9e23194057556798.js": "f1f25dac069b42f9f403e83d10a749c47145c7e6",
    "https://hoangvu1104.github.io/VmuSuperLeague2023/4959.dc2f7d1857d2c212.js": "ff29f8a1fc4f28511e181cdec23fb5e29290f009",
    "https://hoangvu1104.github.io/VmuSuperLeague2023/5168.b871efd2f80b66df.js": "29416fe1e46ebacd43615081b4383303b20bddbd",
    "https://hoangvu1104.github.io/VmuSuperLeague2023/5227.be79798bc07bfd2d.js": "e687509ca461f34cce9d371b57a92f015d37cc36",
    "https://hoangvu1104.github.io/VmuSuperLeague2023/5326.07fb26899d6275e6.js": "e8ab0c5a82d8918d9312df6cd3016f078a275e49",
    "https://hoangvu1104.github.io/VmuSuperLeague2023/5349.db97e0bcf0b1d5c7.js": "d8f735f0e152a5e1f553e797b36098be573eaa10",
    "https://hoangvu1104.github.io/VmuSuperLeague2023/5652.5b508cdc944e8cdb.js": "060c169c53efc4b22d89280fc4bfd06862e2073e",
    "https://hoangvu1104.github.io/VmuSuperLeague2023/5817.939459b690f37977.js": "219dd584cd8efd0e440d443a074373de0af65a70",
    "https://hoangvu1104.github.io/VmuSuperLeague2023/5836.1afb40a2f2e8a43e.js": "d6c0b40bc7ec654b0423e744df1e92a673a2aa21",
    "https://hoangvu1104.github.io/VmuSuperLeague2023/6120.e10bd97ad0fdb89d.js": "76c986fcd6beaa8c9e601892a2bc50ab3234fc40",
    "https://hoangvu1104.github.io/VmuSuperLeague2023/6560.3af818bd483d0781.js": "bba6ed967e7d9f06ec211915f32947c4e8de42ab",
    "https://hoangvu1104.github.io/VmuSuperLeague2023/657.0100b94c3ab93a48.js": "e7f6417f73f497f40e439ed913b80b08d2714a99",
    "https://hoangvu1104.github.io/VmuSuperLeague2023/7070.ae1efda2cc33decc.js": "8b746e97801b6e6dc4d6612a8fbd2b6984eacdeb",
    "https://hoangvu1104.github.io/VmuSuperLeague2023/7206.87b4e433ec6bffb4.js": "22b4dc4028c76b7eb9abd8e6fbb99ebbec1f14ae",
    "https://hoangvu1104.github.io/VmuSuperLeague2023/7544.67b20d4a761e2e38.js": "47dafd65e17ef68ec8ac104e470969aa2cb59a63",
    "https://hoangvu1104.github.io/VmuSuperLeague2023/7602.90dc1e3a0c9814c8.js": "c3d8410ff4634f839ce461312197322750c7edbe",
    "https://hoangvu1104.github.io/VmuSuperLeague2023/8136.78410c20f1e863f9.js": "5d90b57ba7810deb03faf21b2ffb40337d8a6772",
    "https://hoangvu1104.github.io/VmuSuperLeague2023/8628.a088c1cf13dc93d1.js": "ed07fd77c8bb952807b0f3bae119dd9c9275082d",
    "https://hoangvu1104.github.io/VmuSuperLeague2023/8766.86553a4073f31820.js": "796b54789908962d08f7a752eb79c991821653eb",
    "https://hoangvu1104.github.io/VmuSuperLeague2023/8939.4734c10cd219622c.js": "26f4578e648941878f986f15c77d6273f5652b9a",
    "https://hoangvu1104.github.io/VmuSuperLeague2023/9016.c5274acf0968a2f2.js": "2c451b7c61e2e86dff579d2b1f49491bd7460639",
    "https://hoangvu1104.github.io/VmuSuperLeague2023/9230.757cd67fca66f432.js": "bb050cc3f1c1bb477a51ef62c387942735241061",
    "https://hoangvu1104.github.io/VmuSuperLeague2023/9325.5c0b1857766135de.js": "c380454461299d292585544a17e9fc123d3dda92",
    "https://hoangvu1104.github.io/VmuSuperLeague2023/9434.84524f87282c285c.js": "9e8fd85238c2da4b394cc482c2d46ee73ca8494a",
    "https://hoangvu1104.github.io/VmuSuperLeague2023/9536.65a8da2947d76848.js": "3671acdc9c6c785b21f41d8b0d49ffba129a1966",
    "https://hoangvu1104.github.io/VmuSuperLeague2023/9654.97231d17e99b6667.js": "edb9be543d0a8c877dbc2674d462f3e37ca73d7e",
    "https://hoangvu1104.github.io/VmuSuperLeague2023/9824.c512b904cf4c8833.js": "339627d0376ea54aa5d9119bf248addc0c1d6e30",
    "https://hoangvu1104.github.io/VmuSuperLeague2023/9922.44ec96e4d7f86d18.js": "759800f1563375e893f97d98f7f7047a9022fd95",
    "https://hoangvu1104.github.io/VmuSuperLeague2023/9958.3a7943046d5c3504.js": "cc985a805fb56ad90b3a6e9b6cb2a08208fafa34",
    "https://hoangvu1104.github.io/VmuSuperLeague2023/assets/icon/favicon.png": "7798b8e0eb61d7375c245af78bbf5c916932bf13",
    "https://hoangvu1104.github.io/VmuSuperLeague2023/assets/icons/icon-128x128.png": "dae3b6ed49bdaf4327b92531d4b5b4a5d30c7532",
    "https://hoangvu1104.github.io/VmuSuperLeague2023/assets/icons/icon-144x144.png": "b0bd89982e08f9bd2b642928f5391915b74799a7",
    "https://hoangvu1104.github.io/VmuSuperLeague2023/assets/icons/icon-152x152.png": "7479a9477815dfd9668d60f8b3b2fba709b91310",
    "https://hoangvu1104.github.io/VmuSuperLeague2023/assets/icons/icon-192x192.png": "1abd80d431a237a853ce38147d8c63752f10933b",
    "https://hoangvu1104.github.io/VmuSuperLeague2023/assets/icons/icon-384x384.png": "329749cd6393768d3131ed6304c136b1ca05f2fd",
    "https://hoangvu1104.github.io/VmuSuperLeague2023/assets/icons/icon-512x512.png": "559d9c4318b45a1f2b10596bbb4c960fe521dbcc",
    "https://hoangvu1104.github.io/VmuSuperLeague2023/assets/icons/icon-72x72.png": "c457e56089a36952cd67156f9996bc4ce54a5ed9",
    "https://hoangvu1104.github.io/VmuSuperLeague2023/assets/icons/icon-96x96.png": "3914125a4b445bf111c5627875fc190f560daa41",
    "https://hoangvu1104.github.io/VmuSuperLeague2023/assets/images/3MienFC.jpg": "e6a42cac787fdad44dec3e0eb5e93ee3450cbd00",
    "https://hoangvu1104.github.io/VmuSuperLeague2023/assets/images/BFC.JPG": "734d2db44911d73e0a223ec8bfc59690b0439359",
    "https://hoangvu1104.github.io/VmuSuperLeague2023/assets/images/BlueTeam.jpg": "04f749f86ba9641ae6d8bf5c0bdda4ca834472a9",
    "https://hoangvu1104.github.io/VmuSuperLeague2023/assets/images/Logo.png": "18d2db4cd20022e37c73c9c05cd5af8c3656974b",
    "https://hoangvu1104.github.io/VmuSuperLeague2023/assets/images/OrangeTeam.jpg": "8972a1aed3f934902d6e5c9e0871208d9fdc48df",
    "https://hoangvu1104.github.io/VmuSuperLeague2023/assets/images/PinkBlueTeam.jpg": "d850f531e3571b0b9d7ddfa1f34f870e72656634",
    "https://hoangvu1104.github.io/VmuSuperLeague2023/assets/images/PinkTeam.jpg": "047885c989ef23592d01c11206d773f6d20b1448",
    "https://hoangvu1104.github.io/VmuSuperLeague2023/assets/images/PinkTeam2.jpg": "38e99e5f814344d31915bde9bcb7f9331a0e9c8a",
    "https://hoangvu1104.github.io/VmuSuperLeague2023/assets/images/RBJunior.JPG": "91273a9ed5c5668fae9ec34c1a74fa0e60cfacc6",
    "https://hoangvu1104.github.io/VmuSuperLeague2023/assets/images/RedTeam.jpg": "4675e5afebaa2d76e8f82ebb82dc25ed79613383",
    "https://hoangvu1104.github.io/VmuSuperLeague2023/assets/images/Stechco.png": "c9df4924e297fc5e6cc4045fc61e4f27176b0222",
    "https://hoangvu1104.github.io/VmuSuperLeague2023/assets/images/SuperCup.jpg": "2fa2ea043885ac5621ceb8c0f870a5cf4302e1be",
    "https://hoangvu1104.github.io/VmuSuperLeague2023/assets/images/U45FC - Copy.jpg": "bea3dde1108430e2774f733321fc4c9441db390d",
    "https://hoangvu1104.github.io/VmuSuperLeague2023/assets/images/U45FC.jpg": "4e8aafecd08be73e6fc9e0821fb8aedbb768c54b",
    "https://hoangvu1104.github.io/VmuSuperLeague2023/assets/images/VMU.jpg": "22d7185a76da16cacde9768f6078ea875ac10a9f",
    "https://hoangvu1104.github.io/VmuSuperLeague2023/assets/images/WhiteTeam.jpg": "a1288565dcc524eaa670f6af5a560a9529ab5515",
    "https://hoangvu1104.github.io/VmuSuperLeague2023/assets/images/YellowTeam.jpg": "1cb2de87286f0fd3e0810c3f5ac214fd6d135da6",
    "https://hoangvu1104.github.io/VmuSuperLeague2023/assets/shapes.svg": "5413e95adabcb2cb639970051f55e0ddb64ace53",
    "https://hoangvu1104.github.io/VmuSuperLeague2023/common.46ff48aafb75616f.js": "0c8580f282229cd6ae1b35a4f6f40ca62558d0e7",
    "https://hoangvu1104.github.io/VmuSuperLeague2023/index.html": "840cd0770cb5e158435253536d041b9df26c0c02",
    "https://hoangvu1104.github.io/VmuSuperLeague2023/main.0a6797d4ff3f8d97.js": "29543f7ce3ced709d263849e25640aafe9d493b4",
    "https://hoangvu1104.github.io/VmuSuperLeague2023/manifest.webmanifest": "9a088b7c4339228d1082e666ce105dc889bc180c",
    "https://hoangvu1104.github.io/VmuSuperLeague2023/polyfills-core-js.20e9fb5568c66479.js": "7b2237821e79690f9dd2dac0b8a3b9ec6c229b76",
    "https://hoangvu1104.github.io/VmuSuperLeague2023/polyfills-dom.3a5e3168052f1fc5.js": "50f6ff473a0568bffb8a9d412d7efaced2d36137",
    "https://hoangvu1104.github.io/VmuSuperLeague2023/polyfills.fc6fad8ce607b49d.js": "29ecdc4392e1398b433f3838f08631c7ce701c6d",
    "https://hoangvu1104.github.io/VmuSuperLeague2023/runtime.2751a647548631ba.js": "a4ca0f430acea0d1fcc6492b213f3855187d5a4b",
    "https://hoangvu1104.github.io/VmuSuperLeague2023/styles.b8777235688abb5b.css": "55fc6146d8b18952e8a65c1c5c070d08dbea04fd"
  },
  "navigationUrls": [
    {
      "positive": true,
      "regex": "^\\/.*$"
    },
    {
      "positive": false,
      "regex": "^\\/(?:.+\\/)?[^/]*\\.[^/]*$"
    },
    {
      "positive": false,
      "regex": "^\\/(?:.+\\/)?[^/]*__[^/]*$"
    },
    {
      "positive": false,
      "regex": "^\\/(?:.+\\/)?[^/]*__[^/]*\\/.*$"
    }
  ],
  "navigationRequestStrategy": "performance"
}